nbreqs/__init__.py
nbreqs/cli.py
nbreqs-0.2.3.dist-info/LICENSE
nbreqs-0.2.3.dist-info/METADATA
nbreqs-0.2.3.dist-info/WHEEL
nbreqs-0.2.3.dist-info/entry_points.txt
nbreqs-0.2.3.dist-info/RECORD
