Metadata-Version: 2.1
Name: nbreqs
Version: 0.2.3
Summary: Generate notebook_requirements.txt files for Jupyter Notebooks (.ipynb files).
License: MIT
Author: Michel Lavoie
Author-email: lavoie.michel@gmail.com
Requires-Python: >=3.10,<3.13
Classifier: License :: OSI Approved :: MIT License
Classifier: Programming Language :: Python :: 3
Classifier: Programming Language :: Python :: 3.10
Classifier: Programming Language :: Python :: 3.11
Classifier: Programming Language :: Python :: 3.12
Requires-Dist: ipython (>=8.27.0,<9.0.0)
Requires-Dist: nbconvert (>=7.16.4,<8.0.0)
Requires-Dist: requests (>=2.32.3,<3.0.0)
Requires-Dist: rich-click (>=1.8.3,<2.0.0)
Requires-Dist: stdlib-list (>=0.10.0,<0.11.0)
